pingpp/__init__.py
pingpp/api_requestor.py
pingpp/error.py
pingpp/http_client.py
pingpp/pingpp_object.py
pingpp/pingpp_response.py
pingpp/resource.py
pingpp/six.py
pingpp/util.py
pingpp/version.py
pingpp/wxpub_oauth.py
pingpp/api_resources/__init__.py
pingpp/api_resources/agreement.py
pingpp/api_resources/balance_bonus.py
pingpp/api_resources/balance_settlement.py
pingpp/api_resources/balance_transaction.py
pingpp/api_resources/balance_transfer.py
pingpp/api_resources/batch_refund.py
pingpp/api_resources/batch_transfer.py
pingpp/api_resources/batch_withdrawal.py
pingpp/api_resources/card_info.py
pingpp/api_resources/channel.py
pingpp/api_resources/charge.py
pingpp/api_resources/coupon.py
pingpp/api_resources/coupon_template.py
pingpp/api_resources/customs.py
pingpp/api_resources/event.py
pingpp/api_resources/identification.py
pingpp/api_resources/list_object.py
pingpp/api_resources/order.py
pingpp/api_resources/recharge.py
pingpp/api_resources/red_envelope.py
pingpp/api_resources/refund.py
pingpp/api_resources/royalty.py
pingpp/api_resources/royalty_settlement.py
pingpp/api_resources/royalty_template.py
pingpp/api_resources/royalty_transaction.py
pingpp/api_resources/settle_account.py
pingpp/api_resources/sub_app.py
pingpp/api_resources/transfer.py
pingpp/api_resources/user.py
pingpp/api_resources/withdrawal.py
pingpp/api_resources/abstract/__init__.py
pingpp/api_resources/abstract/api_resource.py
pingpp/api_resources/abstract/app_based_api_resource.py
pingpp/api_resources/abstract/createable_api_resource.py
pingpp/api_resources/abstract/createable_app_based_api_resource.py
pingpp/api_resources/abstract/createable_user_based_api_resource.py
pingpp/api_resources/abstract/deletable_api_resource.py
pingpp/api_resources/abstract/deletable_app_based_api_resource.py
pingpp/api_resources/abstract/deletable_user_based_api_resource.py
pingpp/api_resources/abstract/listable_api_resource.py
pingpp-2.7.2.dist-info/METADATA
pingpp-2.7.2.dist-info/RECORD
pingpp-2.7.2.dist-info/WHEEL
pingpp-2.7.2.dist-info/top_level.txt
